radiacaoapp/__init__.py
radiacaoapp-0.0.4.0.dist-info/LICENSE
radiacaoapp-0.0.4.0.dist-info/METADATA
radiacaoapp-0.0.4.0.dist-info/WHEEL
radiacaoapp-0.0.4.0.dist-info/top_level.txt
radiacaoapp-0.0.4.0.dist-info/RECORD
